{
        "code":  "76-897",
        "name":  "Internship: Literary \u0026 Cultural Studies",
        "short_name":  "INTNSHP LTRY CLT STD",
        "units":  12.0,
        "min_units":  12.0,
        "max_units":  12.0,
        "prereqs":  {
                                        "text":  ""
                                },
        "co_reqs":  [

                                ],
        "anti_reqs":  [

                                    ],
        "equiv":  [

                            ],
        "long_desc":  "To be determined",
        "student_sets":  [
                                                {
                                                        "id":  895,
                                                        "name":  "graduate"
                                                }
                                        ],
        "website":  null,
        "custom_fields":  {
                                                    "goals":  null,
                                                    "key_topics":  null,
                                                    "prerequisite_knowledge":  null,
                                                    "assessment_structure":  null,
                                                    "relevance":  null,
                                                    "learning_resources":  null,
                                                    "extra_time_commitment":  null
                                            }
}