{
        "code":  "98-147",
        "name":  "Student Taught Courses (StuCo):Decoding Conspiracies: From Moon Landings to Prin",
        "short_name":  "STUCO: DECOD CONSPIR",
        "units":  3.0,
        "min_units":  3.0,
        "max_units":  3.0,
        "prereqs":  {
                                        "text":  ""
                                },
        "co_reqs":  [

                                ],
        "anti_reqs":  [

                                    ],
        "equiv":  [

                            ],
        "long_desc":  "Is Tupac Really Dead Did Bush Plan 911 Do Aliens Exist Conspiracy theories have existed for centuries and are still growing more popular and wilder over time. In this course, we will discuss, analyze, and validate the most popular conspiracy theories in history. Get prepared to hear some bizarre theories and questions people have about the world we live in.",
        "student_sets":  [
                                                {
                                                        "id":  896,
                                                        "name":  "undergraduate"
                                                }
                                        ],
        "website":  null,
        "custom_fields":  {
                                                    "goals":  null,
                                                    "key_topics":  null,
                                                    "prerequisite_knowledge":  null,
                                                    "assessment_structure":  null,
                                                    "relevance":  null,
                                                    "learning_resources":  null,
                                                    "extra_time_commitment":  null
                                            }
}